Workbook

Sheet Property Summary
A1: Property Name | B1: 2 Example Street MELBOURNE
A2: Purchase Price | B2: 650000
A3: Purchase Date | B3: 46095
A4: Loan Amount | B4: 520000
A5: Interest Rate (%) | B5: 5.5
A6: Loan Term (years) | B6: 30
A7: Total Cash Invested (Deposit + Costs) | B7: 170000
A8: Expected Annual Growth Rate (%) | B8: 4
A9: Expected Annual Rent Growth (%) | B9: 0.1
A10: Expected Annual Expense Growth (%) | B10: 0.5
A12: Annual Net Income | B12: ='Cash Flow'!B3 -> 27095
A13: Annual Cash Flow | B13: ='Cash Flow'!B5 -> -1453
A14: Net Rental Yield | B14: =B12/B2 -> 0.041684615
A15: Cash on Cash Return | B15: =B13/B7 -> -0.0085470588

Sheet Income
A1: Month | B1: Per Week | C1: Rent Received | D1: Other Income | E1: Total Income
A2: Jan | B2: 850 | C2: =B2*(52/12) -> 3683.3333 | D2: 0 | E2: =C2+D2 -> 3683.3333
A3: Feb | B3: 850 | C3: =B3*(52/12) -> 3683.3333 | D3: 0 | E3: =C3+D3 -> 3683.3333
A4: Mar | B4: 850 | C4: =B4*(52/12) -> 3683.3333 | D4: 0 | E4: =C4+D4 -> 3683.3333
A5: Apr | B5: 850 | C5: =B5*(52/12) -> 3683.3333 | D5: 0 | E5: =C5+D5 -> 3683.3333
A6: May | B6: 850 | C6: =B6*(52/12) -> 3683.3333 | D6: 0 | E6: =C6+D6 -> 3683.3333
A7: Jun | B7: 850 | C7: =B7*(52/12) -> 3683.3333 | D7: 0 | E7: =C7+D7 -> 3683.3333
A8: Jul | B8: 850 | C8: =B8*(52/12) -> 3683.3333 | D8: 0 | E8: =C8+D8 -> 3683.3333
A9: Aug | B9: 850 | C9: =B9*(52/12) -> 3683.3333 | D9: 0 | E9: =C9+D9 -> 3683.3333
A10: Sep | B10: 850 | C10: =B10*(52/12) -> 3683.3333 | D10: 0 | E10: =C10+D10 -> 3683.3333
A11: Oct | B11: 850 | C11: =B11*(52/12) -> 3683.3333 | D11: 0 | E11: =C11+D11 -> 3683.3333
A12: Nov | B12: 850 | C12: =B12*(52/12) -> 3683.3333 | D12: 0 | E12: =C12+D12 -> 3683.3333
A13: Dec | B13: 850 | C13: =B13*(52/12) -> 3683.3333 | D13: 0 | E13: =C13+D13 -> 3683.3333
A14: True Annual | E14: =SUM(E2:E13) -> 44200
A15: With 5% Vacancy | E15: =E14*0.95 -> 41990

Sheet Operating Expenses
A1: Category | B1: Monthly | C1: Annual
A2: Property Management | B2: 276.25 | C2: =B2*12 -> 3315
A3: Strata/Body Corporate | B3: 500 | C3: =B3*12 -> 6000
A4: Landloard Insurance | B4: 45 | C4: =B4*12 -> 540
A5: Council Rates | B5: 165 | C5: =B5*12 -> 1980
A6: Maintenance | B6: 150 | C6: =B6*12 -> 1800
A7: Water Service | B7: 80 | C7: =B7*12 -> 960
A8: Other | B8: 25 | C8: =B8*12 -> 300
A9: Total Expenses | C9: =SUM(C2:C8) -> 14895

Sheet Loan Details
A1: Loan Amount | B1: 520000
A2: Interest Rate (%) | B2: 0.0549
A3: Loan Term (years) | B3: 30
A4: Monthly P&I Repayment | B4: =PMT(B2/12,B3*12,-B1) -> 2949.2411
A5: Annual Repayment | B5: =B4*12 -> 35390.893
A6: Monthly I Repayment | B6: =(B1*B2)/12 -> 2379
A7: Annual Repayment | B7: =B6*12 -> 28548
A8: Total Savings of I only | B8: =B5-B7 -> 6842.8929

Sheet Cash Flow
A1: Annual Rental Income | B1: =Income!E15 -> 41990
A2: Annual Operating Expenses | B2: ='Operating Expenses'!C9 -> 14895
A3: Net Operating Income (NOI) | B3: =B1-B2 -> 27095
A4: Annual Debt Service IO | B4: ='Loan Details'!B7 -> 28548
A5: Annual Cash Flow | B5: =B3-B4 -> -1453

Sheet Acquisition Costs
A1: Stamp Duty | B1: 34100
A2: Legal Fees | B2: 1500
A3: Building & Pest Inspection | B3: 600
A4: Loan Setup Fees | B4: 500
A5: Buyers Agent | B5: 5000
A6: Other Costs | B6: 1000
A7: Total Acquisition Costs | B7: =SUM(B1:B6) -> 42700

Sheet Depreciation
A1: Year | B1: Building Depreciation | C1: Fixtures Depreciation | D1: Total Depreciation
A2: 1 | B2: 9000 | C2: 8500 | D2: =B2+C2 -> 17500
A3: 2 | B3: 9000 | C3: 6200 | D3: =B3+C3 -> 15200
A4: 3 | B4: 9000 | C4: 4500 | D4: =B4+C4 -> 13500
A5: 4 | B5: 9000 | C5: 4500 | D5: =B5+C5 -> 13500
A6: 5 | B6: 9000 | C6: 2800 | D6: =B6+C6 -> 11800

Sheet Tax & Negative Gearing
A1: Net Operating Income | B1: ='Cash Flow'!B3 -> 27095
A2: Interest Portion (Est.) | B2: 37000
A3: Other Deductions (Depreciation etc.) | B3: 14000
A4: Taxable Income/Loss | B4: =B1-B2-B3 -> -23905
A5: Marginal Tax Rate (%) | B5: 0.3
A6: Tax Impact (+refund/-payable) | B6: =ABS(B4*(B5)) -> 7171.5

Sheet 10-Year Projection
A1: Year | B1: Property Value | C1: Rental Income | D1: Expenses | E1: Cash Flow | F1: Comment
A2: 1 | B2: ='Property Summary'!B2 -> 650000 | C2: =Income!E14 -> 44200 | D2: ='Operating Expenses'!C9 -> 14895 | E2: =C2-D2-'Loan Details'!B7 -> 757 | F2: Interest Only
A3: 2 | B3: =B2*1.05 -> 682500 | C3: =C2*1.03 -> 45526 | D3: =D2*1.03 -> 15341.85 | E3: =C3-D3-'Loan Details'!B7 -> 1636.15 | F3: Interest Only
A4: 3 | B4: =B3*1.05 -> 716625 | C4: =C3*1.03 -> 46891.78 | D4: =D3*1.03 -> 15802.106 | E4: =C4-D4-'Loan Details'!B5 -> -4301.2184 | F4: P&I
A5: 4 | B5: =B4*1.05 -> 752456.25 | C5: =C4*1.03 -> 48298.533 | D5: =D4*1.03 -> 16276.169 | E5: =C5-D5-'Loan Details'!B5 -> -3368.5282 | F5: P&I
A6: 5 | B6: =B5*1.05 -> 790079.06 | C6: =C5*1.03 -> 49747.489 | D6: =D5*1.03 -> 16764.454 | E6: =C6-D6-'Loan Details'!B5 -> -2407.8573 | F6: P&I
A7: 6 | B7: =B6*1.05 -> 829583.02 | C7: =C6*1.03 -> 51239.914 | D7: =D6*1.03 -> 17267.387 | E7: =C7-D7-'Loan Details'!B5 -> -1418.3662 | F7: P&I
A8: 7 | B8: =B7*1.05 -> 871062.17 | C8: =C7*1.03 -> 52777.112 | D8: =D7*1.03 -> 17785.409 | E8: =C8-D8-'Loan Details'!B5 -> -399.19039 | F8: P&I
A9: 8 | B9: =B8*1.05 -> 914615.27 | C9: =C8*1.03 -> 54360.425 | D9: =D8*1.03 -> 18318.971 | E9: =C9-D9-'Loan Details'!B5 -> 650.56069 | F9: P&I
A10: 9 | B10: =B9*1.05 -> 960346.04 | C10: =C9*1.03 -> 55991.238 | D10: =D9*1.03 -> 18868.54 | E10: =C10-D10-'Loan Details'!B5 -> 1731.8043 | F10: P&I
A11: 10 | B11: =B10*1.05 -> 1008363.3 | C11: =C10*1.03 -> 57670.975 | D11: =D10*1.03 -> 19434.597 | E11: =C11-D11-'Loan Details'!B5 -> 2845.4852 | F11: P&I

Sheet CGT Projection
A1: Estimated Sale Price (Year 10) | B1: ='10-Year Projection'!B11 -> 1008363.3
A2: Purchase Price | B2: ='Property Summary'!B2 -> 650000
A3: Capital Gain | B3: =B1-B2 -> 358363.34
A4: CGT Discount Eligible (50%) | B4: =B3*0.5 -> 179181.67
A5: Marginal Tax Rate (%) | B5: 0.35
A6: Estimated CGT Payable | B6: =B4*(B5) -> 62713.585
